{
  "type": "domain:ChannelProfile",
  "id": "231beabe-7778-47ce-902f-4912e5fbb28c",
  "context_id": "7ac248db-5bfc-4ba1-a324-e11cd9b37edc",
  "platform": "medium",
  "status": "active",
  "format_rules": {
    "min_words": 800,
    "max_words": 2500,
    "structure": "Intro → Problem → MPLP approach → Code/Diagram → Conclusion",
    "use_code_blocks": true,
    "use_mermaid": true,
    "cross_post_to": ["dev.to", "hashnode"],
    "forbidden": [
      "certification",
      "certified",
      "compliance certified",
      "MPLP certified",
      "endorsed by",
      "approved by",
      "framework",
      "product",
      "platform",
      "guaranteed",
      "ensures safety",
      "100% compliant"
    ]
  }
}
